deser/deser.py
deser/test_serializer.py
deser-0.0.2.dist-info/LICENSE
deser-0.0.2.dist-info/METADATA
deser-0.0.2.dist-info/WHEEL
deser-0.0.2.dist-info/top_level.txt
deser-0.0.2.dist-info/RECORD
